keras_autodoc/__init__.py
keras_autodoc/autogen.py
keras_autodoc/docstring.py
keras_autodoc/examples.py
keras_autodoc/gathering_members.py
keras_autodoc/get_signatures.py
keras_autodoc/utils.py
tests/__init__.py
tests/test_autogen.py
tests/test_docstring.py
tests/test_gathering_members.py
tests/test_get_signature.py
tests/test_integration.py
tests/test_utils.py
tests/dummy_package/__init__.py
tests/dummy_package/dummy_module.py
tests/dummy_package/dummy_module2.py
keras_autodoc-0.5.0.dist-info/LICENSE
keras_autodoc-0.5.0.dist-info/METADATA
keras_autodoc-0.5.0.dist-info/WHEEL
keras_autodoc-0.5.0.dist-info/top_level.txt
keras_autodoc-0.5.0.dist-info/RECORD
