Metadata-Version: 2.1
Name: keras-autodoc
Version: 0.5.0
Summary: Building the Keras projects docs.
Home-page: https://github.com/keras-team/keras-autodoc
Author: The Keras team
Author-email: gabrieldemarmiesse@gmail.com
License: Apache License 2.0
Platform: UNKNOWN
Classifier: Natural Language :: English
Classifier: Operating System :: OS Independent
Classifier: Programming Language :: Python :: 3.6
Classifier: Programming Language :: Python :: 3.7
Classifier: Programming Language :: Python :: 3.8
Classifier: Topic :: Utilities
Classifier: Topic :: Documentation
Classifier: Topic :: Software Development :: Libraries :: Python Modules
Classifier: License :: OSI Approved :: Apache Software License
Requires-Dist: markdown
Requires-Dist: sphinx
Requires-Dist: black (==19.10b0)
Provides-Extra: tests
Requires-Dist: pytest ; extra == 'tests'
Requires-Dist: pytest-pep8 ; extra == 'tests'
